pynimcodec/__init__.py
pynimcodec/bitman.py
pynimcodec/cbc/__init__.py
pynimcodec/cbc/application.py
pynimcodec/cbc/codec/__init__.py
pynimcodec/cbc/codec/base_codec.py
pynimcodec/cbc/constants.py
pynimcodec/cbc/field/__init__.py
pynimcodec/cbc/field/array_field.py
pynimcodec/cbc/field/base_field.py
pynimcodec/cbc/field/bitmask_field.py
pynimcodec/cbc/field/bitmaskarray_field.py
pynimcodec/cbc/field/bool_field.py
pynimcodec/cbc/field/calc.py
pynimcodec/cbc/field/common.py
pynimcodec/cbc/field/data_field.py
pynimcodec/cbc/field/enum.py
pynimcodec/cbc/field/enum_field.py
pynimcodec/cbc/field/field_length.py
pynimcodec/cbc/field/float_field.py
pynimcodec/cbc/field/int_field.py
pynimcodec/cbc/field/string_field.py
pynimcodec/cbc/field/struct_field.py
pynimcodec/cbc/field/uint_field.py
pynimcodec/cbc/fileparser.py
pynimcodec/cbc/message/__init__.py
pynimcodec/cbc/message/base_message.py
pynimcodec/nimo/__init__.py
pynimcodec/nimo/base.py
pynimcodec/nimo/constants.py
pynimcodec/nimo/fields/__init__.py
pynimcodec/nimo/fields/array_field.py
pynimcodec/nimo/fields/base_field.py
pynimcodec/nimo/fields/bitmasklist_field.py
pynimcodec/nimo/fields/boolean_field.py
pynimcodec/nimo/fields/data_field.py
pynimcodec/nimo/fields/enum_field.py
pynimcodec/nimo/fields/helpers.py
pynimcodec/nimo/fields/integer_field.py
pynimcodec/nimo/fields/string_field.py
pynimcodec/nimo/message_definitions.py
pynimcodec/nimo/messages.py
pynimcodec/nimo/services.py
pynimcodec/nimo/xmlparser.py
pynimcodec/utils.py
pynimcodec-0.4.15.dist-info/LICENSE
pynimcodec-0.4.15.dist-info/METADATA
pynimcodec-0.4.15.dist-info/WHEEL
pynimcodec-0.4.15.dist-info/RECORD
