Metadata-Version: 2.3
Name: pynimcodec
Version: 0.4.15
Summary: Codecs for Satellite IoT messaging implemented in Python.
License: Apache2.0
Keywords: viasat,inmarsat,satellite,iot,idp,ogx,orbcomm
Author: geoffbrucepayne
Author-email: geoff.bruce-payne@inmarsat.com
Requires-Python: >=3.10,<4.0
Classifier: License :: Other/Proprietary License
Classifier: Programming Language :: Python :: 3
Classifier: Programming Language :: Python :: 3.10
Classifier: Programming Language :: Python :: 3.11
Classifier: Programming Language :: Python :: 3.12
Classifier: Programming Language :: Python :: 3.13
Requires-Dist: aiocoap (>=0.4.12,<0.5.0)
Project-URL: Repository, https://github.com/inmarsat-enterprise/pynimomodem
